{"nodes": [{"id": "c_users_asus_documents_github_waterwallai_ingestion_email_parser_py", "label": "email_parser.py", "file_type": "code", "source_file": "C:\\Users\\Asus\\Documents\\GitHub\\WaterwallAI\\ingestion\\email_parser.py", "source_location": "L1"}, {"id": "ingestion_email_parser_parsedemail", "label": "ParsedEmail", "file_type": "code", "source_file": "C:\\Users\\Asus\\Documents\\GitHub\\WaterwallAI\\ingestion\\email_parser.py", "source_location": "L12"}, {"id": "ingestion_email_parser_parse_eml", "label": "parse_eml()", "file_type": "code", "source_file": "C:\\Users\\Asus\\Documents\\GitHub\\WaterwallAI\\ingestion\\email_parser.py", "source_location": "L21"}, {"id": "ingestion_email_parser_parse_mbox", "label": "parse_mbox()", "file_type": "code", "source_file": "C:\\Users\\Asus\\Documents\\GitHub\\WaterwallAI\\ingestion\\email_parser.py", "source_location": "L35"}, {"id": "ingestion_email_parser_rationale_1", "label": "Deterministic .eml / mbox parser placeholder.", "file_type": "rationale", "source_file": "C:\\Users\\Asus\\Documents\\GitHub\\WaterwallAI\\ingestion\\email_parser.py", "source_location": "L1"}], "edges": [{"source": "c_users_asus_documents_github_waterwallai_ingestion_email_parser_py", "target": "dataclasses", "relation": "imports_from", "context": "import", "confidence": "EXTRACTED", "source_file": "C:\\Users\\Asus\\Documents\\GitHub\\WaterwallAI\\ingestion\\email_parser.py", "source_location": "L4", "weight": 1.0}, {"source": "c_users_asus_documents_github_waterwallai_ingestion_email_parser_py", "target": "datetime", "relation": "imports_from", "context": "import", "confidence": "EXTRACTED", "source_file": "C:\\Users\\Asus\\Documents\\GitHub\\WaterwallAI\\ingestion\\email_parser.py", "source_location": "L5", "weight": 1.0}, {"source": "c_users_asus_documents_github_waterwallai_ingestion_email_parser_py", "target": "email", "relation": "imports_from", "context": "import", "confidence": "EXTRACTED", "source_file": "C:\\Users\\Asus\\Documents\\GitHub\\WaterwallAI\\ingestion\\email_parser.py", "source_location": "L6", "weight": 1.0}, {"source": "c_users_asus_documents_github_waterwallai_ingestion_email_parser_py", "target": "email_parser", "relation": "imports_from", "context": "import", "confidence": "EXTRACTED", "source_file": "C:\\Users\\Asus\\Documents\\GitHub\\WaterwallAI\\ingestion\\email_parser.py", "source_location": "L7", "weight": 1.0}, {"source": "c_users_asus_documents_github_waterwallai_ingestion_email_parser_py", "target": "typing", "relation": "imports_from", "context": "import", "confidence": "EXTRACTED", "source_file": "C:\\Users\\Asus\\Documents\\GitHub\\WaterwallAI\\ingestion\\email_parser.py", "source_location": "L8", "weight": 1.0}, {"source": "c_users_asus_documents_github_waterwallai_ingestion_email_parser_py", "target": "ingestion_email_parser_parsedemail", "relation": "contains", "confidence": "EXTRACTED", "source_file": "C:\\Users\\Asus\\Documents\\GitHub\\WaterwallAI\\ingestion\\email_parser.py", "source_location": "L12", "weight": 1.0}, {"source": "c_users_asus_documents_github_waterwallai_ingestion_email_parser_py", "target": "ingestion_email_parser_parse_eml", "relation": "contains", "confidence": "EXTRACTED", "source_file": "C:\\Users\\Asus\\Documents\\GitHub\\WaterwallAI\\ingestion\\email_parser.py", "source_location": "L21", "weight": 1.0}, {"source": "c_users_asus_documents_github_waterwallai_ingestion_email_parser_py", "target": "ingestion_email_parser_parse_mbox", "relation": "contains", "confidence": "EXTRACTED", "source_file": "C:\\Users\\Asus\\Documents\\GitHub\\WaterwallAI\\ingestion\\email_parser.py", "source_location": "L35", "weight": 1.0}, {"source": "ingestion_email_parser_parse_eml", "target": "ingestion_email_parser_parsedemail", "relation": "calls", "context": "call", "confidence": "EXTRACTED", "source_file": "C:\\Users\\Asus\\Documents\\GitHub\\WaterwallAI\\ingestion\\email_parser.py", "source_location": "L25", "weight": 1.0}, {"source": "ingestion_email_parser_rationale_1", "target": "c_users_asus_documents_github_waterwallai_ingestion_email_parser_py", "relation": "rationale_for", "confidence": "EXTRACTED", "source_file": "C:\\Users\\Asus\\Documents\\GitHub\\WaterwallAI\\ingestion\\email_parser.py", "source_location": "L1", "weight": 1.0}], "raw_calls": [{"caller_nid": "ingestion_email_parser_parse_eml", "callee": "parsebytes", "is_member_call": true, "source_file": "C:\\Users\\Asus\\Documents\\GitHub\\WaterwallAI\\ingestion\\email_parser.py", "source_location": "L22"}, {"caller_nid": "ingestion_email_parser_parse_eml", "callee": "BytesParser", "is_member_call": false, "source_file": "C:\\Users\\Asus\\Documents\\GitHub\\WaterwallAI\\ingestion\\email_parser.py", "source_location": "L22"}, {"caller_nid": "ingestion_email_parser_parse_eml", "callee": "get_body", "is_member_call": true, "source_file": "C:\\Users\\Asus\\Documents\\GitHub\\WaterwallAI\\ingestion\\email_parser.py", "source_location": "L23"}, {"caller_nid": "ingestion_email_parser_parse_eml", "callee": "get_content", "is_member_call": true, "source_file": "C:\\Users\\Asus\\Documents\\GitHub\\WaterwallAI\\ingestion\\email_parser.py", "source_location": "L24"}, {"caller_nid": "ingestion_email_parser_parse_eml", "callee": "get", "is_member_call": true, "source_file": "C:\\Users\\Asus\\Documents\\GitHub\\WaterwallAI\\ingestion\\email_parser.py", "source_location": "L26"}, {"caller_nid": "ingestion_email_parser_parse_eml", "callee": "str", "is_member_call": false, "source_file": "C:\\Users\\Asus\\Documents\\GitHub\\WaterwallAI\\ingestion\\email_parser.py", "source_location": "L27"}, {"caller_nid": "ingestion_email_parser_parse_eml", "callee": "get", "is_member_call": true, "source_file": "C:\\Users\\Asus\\Documents\\GitHub\\WaterwallAI\\ingestion\\email_parser.py", "source_location": "L27"}, {"caller_nid": "ingestion_email_parser_parse_eml", "callee": "strip", "is_member_call": true, "source_file": "C:\\Users\\Asus\\Documents\\GitHub\\WaterwallAI\\ingestion\\email_parser.py", "source_location": "L28"}, {"caller_nid": "ingestion_email_parser_parse_eml", "callee": "split", "is_member_call": true, "source_file": "C:\\Users\\Asus\\Documents\\GitHub\\WaterwallAI\\ingestion\\email_parser.py", "source_location": "L28"}, {"caller_nid": "ingestion_email_parser_parse_eml", "callee": "str", "is_member_call": false, "source_file": "C:\\Users\\Asus\\Documents\\GitHub\\WaterwallAI\\ingestion\\email_parser.py", "source_location": "L28"}, {"caller_nid": "ingestion_email_parser_parse_eml", "callee": "get", "is_member_call": true, "source_file": "C:\\Users\\Asus\\Documents\\GitHub\\WaterwallAI\\ingestion\\email_parser.py", "source_location": "L28"}, {"caller_nid": "ingestion_email_parser_parse_eml", "callee": "strip", "is_member_call": true, "source_file": "C:\\Users\\Asus\\Documents\\GitHub\\WaterwallAI\\ingestion\\email_parser.py", "source_location": "L28"}, {"caller_nid": "ingestion_email_parser_parse_eml", "callee": "str", "is_member_call": false, "source_file": "C:\\Users\\Asus\\Documents\\GitHub\\WaterwallAI\\ingestion\\email_parser.py", "source_location": "L29"}, {"caller_nid": "ingestion_email_parser_parse_eml", "callee": "get", "is_member_call": true, "source_file": "C:\\Users\\Asus\\Documents\\GitHub\\WaterwallAI\\ingestion\\email_parser.py", "source_location": "L29"}, {"caller_nid": "ingestion_email_parser_parse_eml", "callee": "get", "is_member_call": true, "source_file": "C:\\Users\\Asus\\Documents\\GitHub\\WaterwallAI\\ingestion\\email_parser.py", "source_location": "L30"}, {"caller_nid": "ingestion_email_parser_parse_eml", "callee": "get", "is_member_call": true, "source_file": "C:\\Users\\Asus\\Documents\\GitHub\\WaterwallAI\\ingestion\\email_parser.py", "source_location": "L30"}, {"caller_nid": "ingestion_email_parser_parse_mbox", "callee": "NotImplementedError", "is_member_call": false, "source_file": "C:\\Users\\Asus\\Documents\\GitHub\\WaterwallAI\\ingestion\\email_parser.py", "source_location": "L36"}]}